[ 
{ 
"fName" : "Josh",
"lName" : "Forman",
"sexAtBirth" : "M",
"birthDate" : "1970-12-03 00:00:00",
"approxDate" : "exact",
"birthPlace" : null,
"deathDate" : null,
"approxDate" : "exact",
"deathPlace" : null,
"personId" : "@P1@"
},
{ 
"fName" : "Marc",
"lName" : "Forman",
"sexAtBirth" : "M",
"birthDate" : "1946-11-06 00:00:00",
"approxDate" : "exact",
"birthPlace" : "Brooklyn, New York City, New York, USA",
"deathDate" : null,
"approxDate" : "exact",
"deathPlace" : null,
"personId" : "@P2@"
},
{ 
"fName" : "carol",
"lName" : "stumpf",
"sexAtBirth" : "F",
"birthDate" : "1937-01-01 00:00:00",
"approxDate" : "year",
"birthPlace" : "Michigan",
"deathDate" : null,
"approxDate" : "exact",
"deathPlace" : null,
"personId" : "@P3@"
},
{ 
"fName" : "Robert Dean",
"lName" : "Larsen",
"sexAtBirth" : "M",
"birthDate" : "1930-08-24 00:00:00",
"approxDate" : "exact",
"birthPlace" : "Tomah Monroe, Wisconsin",
"deathDate" : "1994-05-29 00:00:00",
"approxDate" : "exact",
"deathPlace" : "Michigan, USA",
"personId" : "@P4@"
},
{ 
"fName" : "gary jay",
"lName" : "hillman",
"sexAtBirth" : "M",
"birthDate" : "1961-01-13 00:00:00",
"approxDate" : "exact",
"birthPlace" : "Chicago, Cook, Illinois, USA",
"deathDate" : null,
"approxDate" : "exact",
"deathPlace" : null,
"personId" : "@P5@"
}
]